ajax_access/__init__.py
ajax_access/settings.py
ajax_access/urls.py
ajax_access/utils.py
ajax_access/views/__init__.py
ajax_access/views/ajax_login.py
ajax_access/views/ajax_logout.py
django_ajax_access-0.2.0.dist-info/LICENSE.txt
django_ajax_access-0.2.0.dist-info/METADATA
django_ajax_access-0.2.0.dist-info/WHEEL
django_ajax_access-0.2.0.dist-info/top_level.txt
django_ajax_access-0.2.0.dist-info/RECORD
