Metadata-Version: 2.1
Name: django-ajax-access
Version: 0.2.0
Summary: A set of views and urls for ajax-based logout and logout for Django
Home-page: https://www.alexseitsinger.com/packages/python/django-ajax-access
Author: Alex Seitsinger
Author-email: software@alexseitsinger.com
License: BSD 2-Clause License
Project-URL: Documentation, https://www.alexseitsinger.com/packages/python/django-ajax-access
Project-URL: Source, https://github.com/alexseitsinger/django-ajax-access
Project-URL: Tracker, https://github.com/alexseitsinger/django-ajax-access/issues
Keywords: django,ajax,login,logout
Platform: UNKNOWN
Classifier: Development Status :: 5 - Production/Stable
Classifier: Environment :: Web Environment
Classifier: Framework :: Django
Classifier: Intended Audience :: Developers
Classifier: License :: OSI Approved :: BSD License
Classifier: Natural Language :: English
Classifier: Operating System :: OS Independent
Classifier: Programming Language :: Python :: 3 :: Only
Classifier: Topic :: Internet :: WWW/HTTP :: Dynamic Content :: Content Management System
Requires-Dist: Django
Requires-Dist: django-ratelimit
